<?xml version="1.0" encoding="UTF-8" standalone="no"?>
<databaseChangeLog xmlns="http://www.liquibase.org/xml/ns/dbchangelog/1.9"
				   xmlns:xsi="http://www.w3.org/2001/XMLSchema-instance"
				   xsi:schemaLocation="http://www.liquibase.org/xml/ns/dbchangelog/1.9 http://www.liquibase.org/xml/ns/dbchangelog/dbchangelog-1.9.xsd">

	<changeSet author="denis" id="2015-11-05-TICKET2627-0">
		<comment>Allow root to edit "File path" property.</comment>
		<update tableName="system">
			<column name="type" value="TEXT"/>
			<where>name = 'filePath'</where>
		</update>
	</changeSet>

</databaseChangeLog>
